nameko_django_gateway_utils/__init__.py
nameko_django_gateway_utils/auth.py
nameko_django_gateway_utils/decorators.py
nameko_django_gateway_utils/exceptions.py
nameko_django_gateway_utils/middlewares.py
nameko_django_gateway_utils/paginations.py
nameko_django_gateway_utils/permissions.py
nameko_django_gateway_utils/requests.py
nameko_django_gateway_utils/response.py
nameko_django_gateway_utils/views.py
nameko_django_gateway_utils/libs/__init__.py
nameko_django_gateway_utils/libs/convertions.py
nameko_django_gateway_utils/libs/import_tools.py
nameko_django_gateway_utils/mixins/__init__.py
nameko_django_gateway_utils/mixins/dispatch.py
nameko_django_gateway_utils-0.0.6.dist-info/LICENSE
nameko_django_gateway_utils-0.0.6.dist-info/METADATA
nameko_django_gateway_utils-0.0.6.dist-info/WHEEL
nameko_django_gateway_utils-0.0.6.dist-info/top_level.txt
nameko_django_gateway_utils-0.0.6.dist-info/RECORD
