Metadata-Version: 2.1
Name: nameko-django-gateway-utils
Version: 0.0.6
Summary: nameko django as gateway utils
Home-page: https://github.com/li1234yun/nameko-django-gateway-utils
Author: li1234yun
Author-email: li1234yun@163.com
License: UNKNOWN
Platform: UNKNOWN
Classifier: Programming Language :: Python :: 3
Classifier: License :: OSI Approved :: MIT License
Classifier: Operating System :: OS Independent
Requires-Dist: nameko
